Metadata-Version: 1.0
Name: lahiru-distributions
Version: 0.4
Summary: Gaussian and Binomial distributions
Home-page: UNKNOWN
Author: Lahiru Senevirathne
Author-email: lahiru.16@cse.mrt.ac.lk
License: UNKNOWN
Platform: UNKNOWN
